bookup_fuse.py
bookup_fuse-0.1.8.dist-info/licenses/LICENSE
bookup_fuse-0.1.8.dist-info/METADATA
bookup_fuse-0.1.8.dist-info/WHEEL
bookup_fuse-0.1.8.dist-info/entry_points.txt
bookup_fuse-0.1.8.dist-info/top_level.txt
bookup_fuse-0.1.8.dist-info/RECORD
