Metadata-Version: 2.4
Name: bookup-fuse
Version: 0.1.8
Summary: Mount Bookup .bdb (SQLite) files as a FUSE filesystem exposing Markdown pages.
Author-email: Frederik <you@example.com>
License: MIT
Project-URL: Homepage, https://example.com/bookup-fuse
Project-URL: Repository, https://github.com/yourname/bookup-fuse
Project-URL: Issues, https://github.com/yourname/bookup-fuse/issues
Keywords: fuse,sqlite,filesystem,markdown,bookup
Classifier: Programming Language :: Python :: 3
Classifier: License :: OSI Approved :: MIT License
Classifier: Operating System :: POSIX :: Linux
Classifier: Topic :: System :: Filesystems
Classifier: Environment :: Console
Requires-Python: >=3.9
License-File: LICENSE
Requires-Dist: fuse-python>=1.0.9
Dynamic: license-file
